README.rst
setup.cfg
setup.py
hexagonit/__init__.py
hexagonit.portletstyle.egg-info/PKG-INFO
hexagonit.portletstyle.egg-info/SOURCES.txt
hexagonit.portletstyle.egg-info/dependency_links.txt
hexagonit.portletstyle.egg-info/entry_points.txt
hexagonit.portletstyle.egg-info/namespace_packages.txt
hexagonit.portletstyle.egg-info/not-zip-safe
hexagonit.portletstyle.egg-info/requires.txt
hexagonit.portletstyle.egg-info/top_level.txt
hexagonit/portletstyle/__init__.py
hexagonit/portletstyle/configure.zcml
hexagonit/portletstyle/interfaces.py
hexagonit/portletstyle/patcher.py
hexagonit/portletstyle/version.txt
hexagonit/portletstyle/vocabulary.py
hexagonit/portletstyle/browser/__init__.py
hexagonit/portletstyle/browser/configure.zcml
hexagonit/portletstyle/browser/controlpanel.py
hexagonit/portletstyle/browser/portletstyle.css
hexagonit/portletstyle/browser/overrides/plone.app.portlets.portlets.events.pt
hexagonit/portletstyle/browser/overrides/plone.app.portlets.portlets.navigation.pt
hexagonit/portletstyle/browser/overrides/plone.app.portlets.portlets.news.pt
hexagonit/portletstyle/browser/overrides/plone.app.portlets.portlets.recent.pt
hexagonit/portletstyle/browser/overrides/plone.app.portlets.portlets.rss.pt
hexagonit/portletstyle/browser/overrides/plone.app.portlets.portlets.search.pt
hexagonit/portletstyle/browser/overrides/plone.portlet.collection.collection.pt
hexagonit/portletstyle/browser/overrides/plone.portlet.static.static.pt
hexagonit/portletstyle/docs/CREDITS.rst
hexagonit/portletstyle/docs/FUTURE.rst
hexagonit/portletstyle/docs/HISTORY.rst
hexagonit/portletstyle/docs/LICENSE.rst
hexagonit/portletstyle/docs/README.rst
hexagonit/portletstyle/docs/conf.py
hexagonit/portletstyle/docs/index.rst
hexagonit/portletstyle/locales/hexagonit.portletstyle.pot
hexagonit/portletstyle/locales/sl/LC_MESSAGES/hexagonit.portletstyle.po
hexagonit/portletstyle/profiles/default/browserlayer.xml
hexagonit/portletstyle/profiles/default/controlpanel.xml
hexagonit/portletstyle/profiles/default/cssregistry.xml
hexagonit/portletstyle/profiles/default/metadata.xml
hexagonit/portletstyle/profiles/default/registry.xml
hexagonit/portletstyle/tests/__init__.py
hexagonit/portletstyle/tests/base.py
hexagonit/portletstyle/tests/test_controlpanel.py
hexagonit/portletstyle/tests/test_docstring.py
hexagonit/portletstyle/tests/test_functional.py
