Metadata-Version: 1.0
Name: hexagonit.portletstyle
Version: 1.3.2
Summary: Assign a CSS style to a portlet
Home-page: http://hexagonit.fi
Author: Hexagon IT
Author-email: oss@hexagonit.fi
License: BSD
Platform: UNKNOWN
Classifier: Framework :: Plone
Classifier: Programming Language :: Python
